setup.py
pexdistributions/Binomialdistribution.py
pexdistributions/Gaussiandistribution.py
pexdistributions/Generaldistribution.py
pexdistributions/__init__.py
pexdistributions.egg-info/PKG-INFO
pexdistributions.egg-info/SOURCES.txt
pexdistributions.egg-info/dependency_links.txt
pexdistributions.egg-info/not-zip-safe
pexdistributions.egg-info/top_level.txt