Metadata-Version: 2.1
Name: pexdistributions
Version: 0.1
Summary: Gaussian distributions
Author: Peter Kamau
